ex2/top.v
/*
 * Based on D. M. Harris and S. L. Harris, "Digital Design and Computer Architecture"
 */
`timescale 1ns / 1ps
 // rename for your .dat-file
`define DATFILE "memfile.dat"

module dmem(
    input  clk, we,
    input  [31:0] a, wd,
    output [31:0] rd);

   reg [31:0] RAM[63:0];
   assign rd = RAM[a[31:2]];
	
   always @ (posedge clk)
     if (we)
       RAM[a[31:2]] <= wd;

   initial
     begin
	$readmemh (`DATFILE, RAM);
     end

endmodule

module imem (
    input  [5:0]  a,
    output [31:0] rd);
				
   reg [31:0]  RAM[63:0];
	
   initial
     begin
	$readmemh (`DATFILE, RAM);
     end
		
   assign rd = RAM[a];
endmodule

module top(
    input clk,
    input reset,
    output [31:0] writedata,
    output [31:0] dataaddr,
    output memwrite
    );

   wire [31:0] pc, instr, readdata;
   // instantiate a processor and memories
   riscv riscv (clk, reset, pc, instr, memwrite, dataaddr, writedata, readdata);
   imem imem (pc[7:2], instr);
   dmem dmem (clk, memwrite, dataaddr, writedata, readdata);
	
endmodule

ex2/alu.v
/*
 * From D. M. Harris and S. L. Harris, "Digital Design and Computer Architecture"
 */
`timescale 1ns / 1ps
module alu(
    input [31:0] srca,
    input [31:0] srcb,
    input [3:0] alucontrol,
    output reg [31:0] aluout,
    output reg btaken
    );

   always @ (*)
     begin
	case (alucontrol)
	  4'b0000: aluout <= srca + srcb;
	  4'b1000: aluout <= srca - srcb;
	  4'b0010: aluout <= $signed(srca) < $signed(srcb);
	  4'b0110: aluout <= srca | srcb;
	  4'b0111: aluout <= srca & srcb;
	endcase
	case (alucontrol) // for conditonal branch
	  4'b0000: btaken <= (srca == srcb) ? 1 : 0;
        endcase
     end
	
endmodule

module alutest;

   reg [31:0] opa, opb;
   reg [3:0]  aluc;
   wire [31:0] res;
   wire        btaken;
   
   alu alu1(opa, opb, aluc, res, btaken);

   initial begin
      $dumpfile("alutest.vcd");
      $dumpvars(0, alutest);
      aluc = 0; #1
      opa = 3; opb = 1;   #1
      aluc = 0; opa = 4; opb = -2; #1

      aluc = 8; #1
      opa = 3; opb = 1;   #1
      aluc = 8; opa = 4; opb = -2; #1
      aluc = 7; #1
      aluc = 6; #1
      aluc = 2; #1
      opa = 3; opb = 3; #1
      opa = 1; opb = 3; #1
      opa = -1; opb = 3; #1
      opa = -1; opb = -2; #1
      opa = -3; opb = -2; #1
      $finish;
   end
   

endmodule // alutest

ex3/datapath.v
/*
 * Based on D. M. Harris and S. L. Harris, "Digital Design and Computer Architecture"
 */
`timescale 1ns / 1ps
module adder(
    input  [31:0] a, b,
    output [31:0] y);

   assign y = a + b;
endmodule

module immext (
    input  i_op,
    input  s_op,
    input  b_op,
    input  u_op,
    input  j_op,
    input [31:0] instr,
    output reg [31:0] y);

   wire [4:0] immtype;

   assign immtype = { i_op, s_op, b_op, u_op, j_op };
   
   always @ (*)
     case (immtype)
       5'b10000: y <= { {20{instr[31]}}, instr[31:20] };
       5'b01000: y <= { {20{instr[31]}}, instr[31:25], instr[11:7] };
       5'b00100: y <= { {19{instr[31]}}, instr[31], instr[7], instr[30:25], instr[11:8], 1'b0 };
       5'b00010: y <= { instr[31:12], 12'b0 };
       5'b00001: y <= { {11{instr[31]}}, instr[31], instr[19:12], instr[20], instr[30:21], 1'b0 };
       default: y <= 'hx;
     endcase // case (immtpe)
   
endmodule

module flopr # (parameter WIDTH = 8)
   (input	clk, reset,
    input	[WIDTH-1:0] d,
    output reg [WIDTH-1:0]  q);
					
   always @ (posedge clk, posedge reset)
     if (reset) q <= 0;
     else	q <= d;
endmodule

module mux2 # (parameter WIDTH = 8)
   (input  [WIDTH-1:0] d0, d1,
    input  s,
    output [WIDTH-1:0] y);
				
   assign y = s ? d1 : d0;
endmodule

module regfile(
    input clk,
    input we3,
    input [4:0] ra1,
    input [4:0] ra2,
    input [4:0] wa3,
    input [31:0] wd3,
    output [31:0] rd1,
    output [31:0] rd2
    );

   reg [31:0] 	  rf[31:0];
	
   // 3-port register file
   always @ (posedge clk)
     if (we3) rf[wa3] <= wd3;
		
   assign rd1 = (ra1 != 0) ? rf[ra1] : 0;
   assign rd2 = (ra2 != 0) ? rf[ra2] : 0;
endmodule

module datapath(
    input  clk,
    input  reset,
    input  memtoreg,
    input  pcsrc,
    input  alusrc,
    input  regwrite,
    input  i_op,
    input  s_op,
    input  b_op,
    input  u_op,
    input  j_op,
    input  [3:0] alucontrol,
    output btaken,
    output [31:0] pc,
    input  [31:0] instr,
    output [31:0] aluout,
    output [31:0] writedata,
    input  [31:0] readdata
    );

   wire [31:0] 	 pcnext, pcplus4, pcbranch;
   wire [31:0] 	 immextv;
   wire [31:0] 	 rsrca, srca, srcb;
   wire [31:0] 	 result0, result;
	
   // exploit immediate
   immext	ie(i_op, s_op, b_op, u_op, j_op, instr, immextv);

   // for next PC
   flopr #(32)	pcreg(clk, reset, pcnext, pc);
   adder	pcadd1 (pc, 32'b100, pcplus4);
   adder	pcadd2(pc, immextv, pcbranch);
   mux2 #(32)   pcmux(pcplus4, pcbranch, (pcsrc|j_op), pcnext);
							
   // reg-file logic
   regfile	rf(clk, regwrite, instr[19:15], instr[24:20], instr[11:7],
		   result, rsrca, writedata);
   mux2 #(32)	resmux1(aluout, readdata, memtoreg, result0);
   mux2 #(32)	resmux2(result0, pcplus4, j_op, result);
	
   // ALU logic
   mux2 #(32) srcamux(rsrca, 32'h0, u_op, srca);
   mux2 #(32) srcbmux(writedata, immextv, alusrc, srcb);
   alu alu(srca, srcb, alucontrol, aluout, btaken);
endmodule

module testdp;
   reg clk;
   reg reset;
   reg memtoreg, pcsrc, alusrc, regwrite;
   reg i_op, s_op, b_op, u_op, j_op;
   reg [3:0] alucontrol;
   reg [31:0] instr;
   reg [31:0] readdata;
   wire btaken;
   wire [31:0] pc;
   wire [31:0] aluout;
   wire [31:0] writedata;

   datapath dp(clk, reset, memtoreg, pcsrc, alusrc, regwrite,
	       i_op, s_op, b_op, u_op, j_op, alucontrol, btaken, pc,
	       instr, aluout, writedata, readdata);

   initial begin
      $dumpfile("testdp.vcd");
      $dumpvars(0, testdp);
      clk = 1; reset = 1; memtoreg = 0; pcsrc = 0; alusrc = 0; regwrite = 1;
      instr = 32'hdeadbeaf;
      i_op = 0; s_op = 0; b_op = 0; u_op = 0; j_op = 0;
      alucontrol = 0;
      readdata = 0; #1
      reset = 0; clk = 0; #1
      clk = 1; #1
      clk = 0; #1
      clk = 1; i_op = 1; #1
      clk = 0; #1
      clk = 1; i_op = 0; s_op = 1; #1
      clk = 0; #1
      clk = 1; s_op = 0; b_op = 1; #1
      clk = 0; #1
      clk = 1; b_op = 0; u_op = 1; #1
      clk = 0; #1
      clk = 1; u_op = 0; j_op = 1; #1
      clk = 0; #1
      clk = 1; instr = 32'h5eadbeaf; j_op = 0; i_op = 1; #1
      clk = 0; #1
      clk = 1; i_op = 0; s_op = 1; #1
      clk = 0; #1
      clk = 1; s_op = 0; b_op = 1; #1
      clk = 0; #1
      clk = 1; b_op = 0; u_op = 1; #1
      clk = 0; #1
      clk = 1; u_op = 0; j_op = 1; #1
      clk = 0; #1
      clk = 1; readdata = 32'hf; memtoreg = 1; regwrite = 1; j_op = 0; i_op = 1; instr = 32'hde108080; #1
      clk = 0; #1
      clk = 1; #1
      clk = 0; #1
      clk = 1; regwrite = 0; alusrc = 0; #1
      clk = 0; #1
      clk = 1; alusrc = 1; #1
      clk = 0; #1
      clk = 1; pcsrc = 1; #1
      clk = 0; #1
      clk = 1; #1
      clk = 0; #1
      $finish;
   end
endmodule // testdp

ex3/controller.v
/*
 * Based on D. M. Harris and S. L. Harris, "Digital Design and Computer Architecture"
 */
`timescale 1ns / 1ps
module maindec(
    input [6:0] op,
    output memtoreg,
    output memwrite,
    output alusrc,
    output regwrite,
    output r_op,
    output i_op,
    output s_op,
    output b_op,
    output u_op,
    output j_op,

    output [2:0] aluop
    );

   reg [12:0] 	 controls;
	
   assign { regwrite, alusrc, memwrite, memtoreg,
            r_op, i_op, s_op, b_op, u_op, j_op, aluop } = controls;
				
   always @ (*)
     case (op)
       7'b0110011: controls <= 13'b1000100000100; //Rtype
       7'b0010011: controls <= 13'b1100010000101; //Itype
       7'b1100011: controls <= 13'b0000000100110; //Btype
       7'b0000011: controls <= 13'b1101010000111; //LW
       7'b0100011: controls <= 13'b0110001000111; //SW
       7'b0110111: controls <= 13'b1100000010011; //LUI
       7'b1101111: controls <= 13'b1000000001000; //JAL
       default:    controls <= 13'bxxxxxxxxxxxxx; //???
     endcase

endmodule

module aludec(
    input [2:0]      funct3,
    input [6:0]      funct7,
    input            r_op,
    input [2:0]      aluop,
    output reg [3:0] alucontrol
    );

   wire exf7;
   assign exf7 = (r_op & ((funct7 == 7'b0100000 ) ? 1'b1 : ((funct7 == 7'b0000000 ) ? 1'b0 : 1'bx)));
   
   always @ (*)
     case (aluop)
       3'b000: alucontrol <= 4'b0000; // addition
       3'b011: alucontrol <= 4'b0110; // or
       3'b100: alucontrol <= {exf7, funct3}; // R-type
       3'b101: alucontrol <= {1'b0, funct3}; // I-type
       3'b110: alucontrol <= {1'b0, funct3}; // B-type
       3'b111: case (funct3) // L-type or S-type
                 3'b010: alucontrol <= 4'b0000; // LW or SW
                 default: alucontrol <= 4'bxxxx;
               endcase
      default: alucontrol <= 4'bxxxx; //???
     endcase
endmodule

module controller(
    input [6:0] op,
    input [2:0] funct3,
    input [6:0] funct7,
    input btaken,
    output memtoreg,
    output memwrite,
    output pcsrc,
    output alusrc,
    output regwrite,
    output r_op,
    output i_op,
    output s_op,
    output b_op,
    output u_op,
    output j_op,
    output [3:0] alucontrol
    );

   wire [2:0] 	 aluop;
	
   maindec md (op, memtoreg, memwrite, alusrc, regwrite,
               r_op, i_op, s_op, b_op, u_op, j_op, aluop);
   aludec ad (funct3, funct7, r_op, aluop, alucontrol);
	
   assign pcsrc = b_op & btaken;
endmodule

module testcont;
   reg [6:0] op;
   reg [2:0] funct3;
   reg [6:0] funct7;
   reg 	     btaken;
   wire      memtoreg, memwrite, pcsrc, alusrc, regwrite;
   wire      r_op, i_op, s_op, b_op, u_op, j_op;
   wire [3:0] alucontrol;

   controller ctl(op, funct3, funct7, btaken, memtoreg, memwrite, pcsrc,
		  alusrc, regwrite, r_op, i_op, s_op, b_op, u_op, j_op,
                  alucontrol);

   initial begin
      $dumpfile("testcont.vcd");
      $dumpvars(0, testcont);
      btaken = 0; op = 'h33; funct3 = 'h0; funct7 = 'h0; #1
      funct3 = 'h0; funct7 = 'h20; #1
      funct3 = 'h7; funct7 = 'h0; #1
      funct3 = 'h6; funct7 = 'h0; #1
      funct3 = 'h2; funct7 = 'h0; #1
      op = 'h3; funct3 = 2; #1
      op = 'h23; funct3 = 2; #1
      op = 'h13; funct3 = 0; #1
      op = 'h13; funct3 = 6; #1
      op = 'h37; #1
      op = 'h6f; #1
      $finish;
   end
endmodule // testcont

ex2/riscv.v
/*
 * Based on D. M. Harris and S. L. Harris, "Digital Design and Computer Architecture"
 */
`timescale 1ns / 1ps
module riscv(
    input  clk,
    input  reset,
    output [31:0] pc,
    input  [31:0] instr,
    output memwrite,
    output [31:0] aluout,
    output [31:0] writedata,
    input  [31:0] readdata
    );

   wire 	  memtoreg, branch, alusrc, regdst, regwrite, jump, btaken;
   wire [1:0] 	  immtype;
 	  
   wire [3:0] 	  alucontrol;
	
   controller ctl(instr[6:0], instr[14:12], instr[31:25], btaken,
                  memtoreg, memwrite, pcsrc, alusrc, regwrite,
                  r_op, i_op, s_op, b_op, u_op, j_op, alucontrol);
   datapath dp(clk, reset, memtoreg, pcsrc, alusrc, regwrite,
               i_op, s_op, b_op, u_op, j_op, alucontrol,
               btaken, pc, instr, aluout, writedata, readdata);
					
endmodule

ex2/testbench.v
/*
 * From D. M. Harris and S. L. Harris, "Digital Design and Computer Architecture"
 */
`timescale 1ns / 1ps
module testbench();

   reg	clk;
   reg	reset;
	
   wire [31:0] writedata, dataaddr;
   wire        memwrite;
	
   // instantiate device to be tested
   top dut (clk, reset, writedata, dataaddr, memwrite);
	
   // initialize test
   initial begin
      $dumpfile("testb.vcd");
      $dumpvars(0, testbench);
      reset <= 1; # 22; reset <= 0;
   end
		
   // generate clock to sequence tests
   always
     begin
	clk <= 1; #5; clk <= 0; #5;
     end
		
   // check results
   always @ (negedge clk)
     begin
	if (memwrite & dataaddr === 84) begin
           if (writedata === 33054) begin
	      $display ("Simulation succeeded");
	      $finish;
           end else begin
	      $display ("Simulation partially succeeded");
	      $finish;
           end
	end
     end

endmodule

ex2/testb.vcd
$date
	Thu Oct 30 12:54:11 2025
$end
$version
	Icarus Verilog
$end
$timescale
	1ps
$end
$scope module testbench $end
$var wire 32 ! writedata [31:0] $end
$var wire 1 " memwrite $end
$var wire 32 # dataaddr [31:0] $end
$var reg 1 $ clk $end
$var reg 1 % reset $end
$scope module dut $end
$var wire 1 $ clk $end
$var wire 1 % reset $end
$var wire 32 & writedata [31:0] $end
$var wire 32 ' readdata [31:0] $end
$var wire 32 ( pc [31:0] $end
$var wire 1 " memwrite $end
$var wire 32 ) instr [31:0] $end
$var wire 32 * dataaddr [31:0] $end
$scope module dmem $end
$var wire 1 $ clk $end
$var wire 32 + rd [31:0] $end
$var wire 1 " we $end
$var wire 32 , wd [31:0] $end
$var wire 32 - a [31:0] $end
$upscope $end
$scope module imem $end
$var wire 6 . a [5:0] $end
$var wire 32 / rd [31:0] $end
$upscope $end
$scope module riscv $end
$var wire 1 $ clk $end
$var wire 32 0 instr [31:0] $end
$var wire 32 1 readdata [31:0] $end
$var wire 1 % reset $end
$var wire 32 2 writedata [31:0] $end
$var wire 1 3 u_op $end
$var wire 1 4 s_op $end
$var wire 1 5 regwrite $end
$var wire 1 6 r_op $end
$var wire 1 7 pcsrc $end
$var wire 32 8 pc [31:0] $end
$var wire 1 " memwrite $end
$var wire 1 9 memtoreg $end
$var wire 1 : j_op $end
$var wire 1 ; i_op $end
$var wire 1 < btaken $end
$var wire 1 = b_op $end
$var wire 1 > alusrc $end
$var wire 32 ? aluout [31:0] $end
$var wire 4 @ alucontrol [3:0] $end
$scope module ctl $end
$var wire 3 A funct3 [2:0] $end
$var wire 7 B funct7 [6:0] $end
$var wire 7 C op [6:0] $end
$var wire 1 7 pcsrc $end
$var wire 1 3 u_op $end
$var wire 1 4 s_op $end
$var wire 1 5 regwrite $end
$var wire 1 6 r_op $end
$var wire 1 " memwrite $end
$var wire 1 9 memtoreg $end
$var wire 1 : j_op $end
$var wire 1 ; i_op $end
$var wire 1 < btaken $end
$var wire 1 = b_op $end
$var wire 1 > alusrc $end
$var wire 3 D aluop [2:0] $end
$var wire 4 E alucontrol [3:0] $end
$scope module ad $end
$var wire 1 F exf7 $end
$var wire 3 G funct3 [2:0] $end
$var wire 7 H funct7 [6:0] $end
$var wire 1 6 r_op $end
$var wire 3 I aluop [2:0] $end
$var reg 4 J alucontrol [3:0] $end
$upscope $end
$scope module md $end
$var wire 7 K op [6:0] $end
$var wire 1 3 u_op $end
$var wire 1 4 s_op $end
$var wire 1 5 regwrite $end
$var wire 1 6 r_op $end
$var wire 1 " memwrite $end
$var wire 1 9 memtoreg $end
$var wire 1 : j_op $end
$var wire 1 ; i_op $end
$var wire 1 = b_op $end
$var wire 1 > alusrc $end
$var wire 3 L aluop [2:0] $end
$var reg 13 M controls [12:0] $end
$upscope $end
$upscope $end
$scope module dp $end
$var wire 4 N alucontrol [3:0] $end
$var wire 1 > alusrc $end
$var wire 1 = b_op $end
$var wire 1 $ clk $end
$var wire 1 ; i_op $end
$var wire 32 O instr [31:0] $end
$var wire 1 : j_op $end
$var wire 1 9 memtoreg $end
$var wire 1 7 pcsrc $end
$var wire 32 P readdata [31:0] $end
$var wire 1 5 regwrite $end
$var wire 1 % reset $end
$var wire 1 4 s_op $end
$var wire 1 3 u_op $end
$var wire 32 Q writedata [31:0] $end
$var wire 32 R srcb [31:0] $end
$var wire 32 S srca [31:0] $end
$var wire 32 T rsrca [31:0] $end
$var wire 32 U result0 [31:0] $end
$var wire 32 V result [31:0] $end
$var wire 32 W pcplus4 [31:0] $end
$var wire 32 X pcnext [31:0] $end
$var wire 32 Y pcbranch [31:0] $end
$var wire 32 Z pc [31:0] $end
$var wire 32 [ immextv [31:0] $end
$var wire 1 < btaken $end
$var wire 32 \ aluout [31:0] $end
$scope module alu $end
$var wire 4 ] alucontrol [3:0] $end
$var wire 32 ^ srcb [31:0] $end
$var wire 32 _ srca [31:0] $end
$var reg 32 ` aluout [31:0] $end
$var reg 1 < btaken $end
$upscope $end
$scope module ie $end
$var wire 1 = b_op $end
$var wire 1 ; i_op $end
$var wire 32 a instr [31:0] $end
$var wire 1 : j_op $end
$var wire 1 4 s_op $end
$var wire 1 3 u_op $end
$var wire 5 b immtype [4:0] $end
$var reg 32 c y [31:0] $end
$upscope $end
$scope module pcadd1 $end
$var wire 32 d b [31:0] $end
$var wire 32 e y [31:0] $end
$var wire 32 f a [31:0] $end
$upscope $end
$scope module pcadd2 $end
$var wire 32 g b [31:0] $end
$var wire 32 h y [31:0] $end
$var wire 32 i a [31:0] $end
$upscope $end
$scope module pcmux $end
$var wire 32 j d0 [31:0] $end
$var wire 32 k d1 [31:0] $end
$var wire 1 l s $end
$var wire 32 m y [31:0] $end
$var parameter 32 n WIDTH $end
$upscope $end
$scope module pcreg $end
$var wire 1 $ clk $end
$var wire 32 o d [31:0] $end
$var wire 1 % reset $end
$var parameter 32 p WIDTH $end
$var reg 32 q q [31:0] $end
$upscope $end
$scope module resmux1 $end
$var wire 32 r d0 [31:0] $end
$var wire 32 s d1 [31:0] $end
$var wire 1 9 s $end
$var wire 32 t y [31:0] $end
$var parameter 32 u WIDTH $end
$upscope $end
$scope module resmux2 $end
$var wire 32 v d0 [31:0] $end
$var wire 32 w d1 [31:0] $end
$var wire 1 : s $end
$var wire 32 x y [31:0] $end
$var parameter 32 y WIDTH $end
$upscope $end
$scope module rf $end
$var wire 1 $ clk $end
$var wire 5 z ra1 [4:0] $end
$var wire 5 { ra2 [4:0] $end
$var wire 5 | wa3 [4:0] $end
$var wire 32 } wd3 [31:0] $end
$var wire 1 5 we3 $end
$var wire 32 ~ rd2 [31:0] $end
$var wire 32 !" rd1 [31:0] $end
$upscope $end
$scope module srcamux $end
$var wire 32 "" d0 [31:0] $end
$var wire 32 #" d1 [31:0] $end
$var wire 1 3 s $end
$var wire 32 $" y [31:0] $end
$var parameter 32 %" WIDTH $end
$upscope $end
$scope module srcbmux $end
$var wire 32 &" d0 [31:0] $end
$var wire 32 '" d1 [31:0] $end
$var wire 1 > s $end
$var wire 32 (" y [31:0] $end
$var parameter 32 )" WIDTH $end
$upscope $end
$upscope $end
$upscope $end
$upscope $end
$upscope $end
$enddefinitions $end
$comment Show the parameter values. $end
$dumpall
b100000 )"
b100000 %"
b100000 y
b100000 u
b100000 p
b100000 n
$end
#0
$dumpvars
b1000000000000000 ("
b1000000000000000 '"
b0 &"
b0 $"
b0 #"
bx ""
bx !"
b0 ~
b1000000000000000 }
b1 |
b0 {
b1 z
b1000000000000000 x
b100 w
b1000000000000000 v
b1000000000000000 t
bx s
b1000000000000000 r
b0 q
b100 o
b100 m
0l
b1000000000000000 k
b100 j
b0 i
b1000000000000000 h
b1000000000000000 g
b0 f
b100 e
b100 d
b1000000000000000 c
b10 b
b1000000010110111 a
b1000000000000000 `
b0 _
b1000000000000000 ^
b110 ]
b1000000000000000 \
b1000000000000000 [
b0 Z
b1000000000000000 Y
b100 X
b100 W
b1000000000000000 V
b1000000000000000 U
bx T
b0 S
b1000000000000000 R
b0 Q
bx P
b1000000010110111 O
b110 N
b1100000010011 M
b11 L
b110111 K
b110 J
b11 I
b0 H
b0 G
0F
b110 E
b11 D
b110111 C
b0 B
b0 A
b110 @
b1000000000000000 ?
1>
0=
x<
0;
0:
09
b0 8
07
06
15
04
13
b0 2
bx 1
b1000000010110111 0
b1000000010110111 /
b0 .
b1000000000000000 -
b0 ,
bx +
b1000000000000000 *
b1000000010110111 )
b0 (
bx '
b0 &
1%
1$
b1000000000000000 #
0"
b0 !
$end
#5000
0$
#10000
b1000000000000000 T
b1000000000000000 !"
b1000000000000000 ""
1$
#15000
0$
#20000
1$
#22000
0%
#25000
0$
#30000
b1000000010110111 '
b1000000010110111 +
b1000000010110111 1
b1000000010110111 P
b1000000010110111 s
0<
b1 V
b1 x
b1 }
b1 U
b1 t
b1 v
b0 @
b0 E
b0 J
b0 N
b0 ]
b1 #
b1 *
b1 -
b1 ?
b1 \
b1 `
b1 r
1;
b10000 b
03
b101 D
b101 I
b101 L
b1 R
b1 ^
b1 ("
b1100010000101 M
b1 [
b1 c
b1 g
b1 '"
b0 T
b0 !"
b0 ""
b1000000000000000 !
b1000000000000000 &
b1000000000000000 ,
b1000000000000000 2
b1000000000000000 Q
b1000000000000000 ~
b1000000000000000 &"
b10011 C
b10011 K
b0 z
b1 {
b10 |
b1000 X
b1000 m
b1000 o
b100000000000100010011 )
b100000000000100010011 /
b100000000000100010011 0
b100000000000100010011 O
b100000000000100010011 a
b1 .
b101 Y
b101 h
b101 k
b1000 W
b1000 e
b1000 j
b1000 w
b100 (
b100 8
b100 Z
b100 f
b100 i
b100 q
1$
#35000
0$
#40000
b1011 V
b1011 x
b1011 }
b1011 U
b1011 t
b1011 v
b101100000000000110010011 '
b101100000000000110010011 +
b101100000000000110010011 1
b101100000000000110010011 P
b101100000000000110010011 s
b1011 #
b1011 *
b1011 -
b1011 ?
b1011 \
b1011 `
b1011 r
b1011 R
b1011 ^
b1011 ("
b1011 [
b1011 c
b1011 g
b1011 '"
bx !
bx &
bx ,
bx 2
bx Q
bx ~
bx &"
b1011 {
b11 |
b1100 X
b1100 m
b1100 o
b101100000000000110010011 )
b101100000000000110010011 /
b101100000000000110010011 0
b101100000000000110010011 O
b101100000000000110010011 a
b10 .
b10011 Y
b10011 h
b10011 k
b1100 W
b1100 e
b1100 j
b1100 w
b1000 (
b1000 8
b1000 Z
b1000 f
b1000 i
b1000 q
1$
#45000
0$
#50000
b1 V
b1 x
b1 }
b1 U
b1 t
b1 v
b1000000010110111 '
b1000000010110111 +
b1000000010110111 1
b1000000010110111 P
b1000000010110111 s
b1 #
b1 *
b1 -
b1 ?
b1 \
b1 `
b1 r
b1 R
b1 ^
b1 ("
b1 [
b1 c
b1 g
b1 '"
b1000000000000000 !
b1000000000000000 &
b1000000000000000 ,
b1000000000000000 2
b1000000000000000 Q
b1000000000000000 ~
b1000000000000000 &"
b1 {
b100 |
b10000 X
b10000 m
b10000 o
b100000000001000010011 )
b100000000001000010011 /
b100000000001000010011 0
b100000000001000010011 O
b100000000001000010011 a
b11 .
b1101 Y
b1101 h
b1101 k
b10000 W
b10000 e
b10000 j
b10000 w
b1100 (
b1100 8
b1100 Z
b1100 f
b1100 i
b1100 q
1$
#55000
0$
#60000
b1 V
b1 x
b1 }
b1 U
b1 t
b1 v
1<
b1 #
b1 *
b1 -
b1 ?
b1 \
b1 `
b1 r
b111 @
b111 E
b111 J
b111 N
b111 ]
b1 S
b1 _
b1 $"
b1 T
b1 !"
b1 ""
b111 A
b111 G
b10 z
b101 |
b10100 X
b10100 m
b10100 o
b100010111001010010011 )
b100010111001010010011 /
b100010111001010010011 0
b100010111001010010011 O
b100010111001010010011 a
b100 .
b10001 Y
b10001 h
b10001 k
b10100 W
b10100 e
b10100 j
b10100 w
b10000 (
b10000 8
b10000 Z
b10000 f
b10000 i
b10000 q
1$
#65000
0$
#70000
b10 V
b10 x
b10 }
b10 U
b10 t
b10 v
1<
b10 #
b10 *
b10 -
b10 ?
b10 \
b10 `
b10 r
1l
17
05
0>
0;
b100 b
1=
b110 D
b110 I
b110 L
b1 R
b1 ^
b1 ("
b100110 M
b0 @
b0 E
b0 J
b0 N
b0 ]
b1000 [
b1000 c
b1000 g
b1000 '"
b1 !
b1 &
b1 ,
b1 2
b1 Q
b1 ~
b1 &"
b1100011 C
b1100011 K
b0 A
b0 G
b101 z
b100 {
b1000 |
b11100 X
b11100 m
b11100 o
b10000101000010001100011 )
b10000101000010001100011 /
b10000101000010001100011 0
b10000101000010001100011 O
b10000101000010001100011 a
b101 .
b11100 Y
b11100 h
b11100 k
b11000 W
b11000 e
b11000 j
b11000 w
b10100 (
b10100 8
b10100 Z
b10100 f
b10100 i
b10100 q
1$
#75000
0$
#80000
0l
b10 V
b10 x
b10 }
07
b10 U
b10 t
b10 v
b1000000010110111 '
b1000000010110111 +
b1000000010110111 1
b1000000010110111 P
b1000000010110111 s
15
1>
1;
b10000 b
0=
b101 D
b101 I
b101 L
1<
b10 #
b10 *
b10 -
b10 ?
b10 \
b10 `
b10 r
b1100010000101 M
b1 [
b1 c
b1 g
b1 '"
b1 R
b1 ^
b1 ("
b1000000000000000 !
b1000000000000000 &
b1000000000000000 ,
b1000000000000000 2
b1000000000000000 Q
b1000000000000000 ~
b1000000000000000 &"
b10011 C
b10011 K
b10 z
b1 {
b10 |
b100000 X
b100000 m
b100000 o
b100010000000100010011 )
b100010000000100010011 /
b100010000000100010011 0
b100010000000100010011 O
b100010000000100010011 a
b111 .
b11101 Y
b11101 h
b11101 k
b100000 W
b100000 e
b100000 j
b100000 w
b11100 (
b11100 8
b11100 Z
b11100 f
b11100 i
b11100 q
1$
#85000
0$
#90000
b1 V
b1 x
b1 }
b1 U
b1 t
b1 v
0>
16
b0 b
0;
b100 D
b100 I
b100 L
b1011 R
b1011 ^
b1011 ("
0<
b1 #
b1 *
b1 -
b1 ?
b1 \
b1 `
b1 r
b1000100000100 M
b10 @
b10 E
b10 J
b10 N
b10 ]
bx [
bx c
bx g
bx '"
b1011 !
b1011 &
b1011 ,
b1011 2
b1011 Q
b1011 ~
b1011 &"
b10 S
b10 _
b10 $"
b110011 C
b110011 K
b10 A
b10 G
b11 {
b101 |
b10 T
b10 !"
b10 ""
b100100 X
b100100 m
b100100 o
b1100010010001010110011 )
b1100010010001010110011 /
b1100010010001010110011 0
b1100010010001010110011 O
b1100010010001010110011 a
b1000 .
bx Y
bx h
bx k
b100100 W
b100100 e
b100100 j
b100100 w
b100000 (
b100000 8
b100000 Z
b100000 f
b100000 i
b100000 q
1$
#95000
0$
#100000
1l
17
1<
b10000 Y
b10000 h
b10000 k
b11111111111111111111111111101100 [
b11111111111111111111111111101100 c
b11111111111111111111111111101100 g
b11111111111111111111111111101100 '"
b10 V
b10 x
b10 }
b10 U
b10 t
b10 v
05
06
b100 b
1=
b110 D
b110 I
b110 L
b10 #
b10 *
b10 -
b10 ?
b10 \
b10 `
b10 r
b100110 M
b0 @
b0 E
b0 J
b0 N
b0 ]
0F
b1 S
b1 _
b1 $"
b1 R
b1 ^
b1 ("
b1 T
b1 !"
b1 ""
b1 !
b1 &
b1 ,
b1 2
b1 Q
b1 ~
b1 &"
b1100011 C
b1100011 K
b0 A
b0 G
b1111111 B
b1111111 H
b101 z
b100 {
b1101 |
b10000 X
b10000 m
b10000 o
b11111110010000101000011011100011 )
b11111110010000101000011011100011 /
b11111110010000101000011011100011 0
b11111110010000101000011011100011 O
b11111110010000101000011011100011 a
b1001 .
b101000 W
b101000 e
b101000 j
b101000 w
b100100 (
b100100 8
b100100 Z
b100100 f
b100100 i
b100100 q
1$
#105000
0$
#110000
0l
b0 V
b0 x
b0 }
07
b0 U
b0 t
b0 v
b1000000010110111 '
b1000000010110111 +
b1000000010110111 1
b1000000010110111 P
b1000000010110111 s
15
1>
1;
b10000 b
0=
b101 D
b101 I
b101 L
0<
b0 #
b0 *
b0 -
b0 ?
b0 \
b0 `
b0 r
b1100010000101 M
b111 @
b111 E
b111 J
b111 N
b111 ]
b1 [
b1 c
b1 g
b1 '"
b10 S
b10 _
b10 $"
b1 R
b1 ^
b1 ("
b10 T
b10 !"
b10 ""
b1000000000000000 !
b1000000000000000 &
b1000000000000000 ,
b1000000000000000 2
b1000000000000000 Q
b1000000000000000 ~
b1000000000000000 &"
b10011 C
b10011 K
b111 A
b111 G
b0 B
b0 H
b10 z
b1 {
b101 |
b10100 X
b10100 m
b10100 o
b100010111001010010011 )
b100010111001010010011 /
b100010111001010010011 0
b100010111001010010011 O
b100010111001010010011 a
b100 .
b10001 Y
b10001 h
b10001 k
b10100 W
b10100 e
b10100 j
b10100 w
b10000 (
b10000 8
b10000 Z
b10000 f
b10000 i
b10000 q
1$
#115000
0$
#120000
b1 V
b1 x
b1 }
b1 U
b1 t
b1 v
b1 #
b1 *
b1 -
b1 ?
b1 \
b1 `
b1 r
05
0>
0;
b100 b
1=
b110 D
b110 I
b110 L
b1 R
b1 ^
b1 ("
b100110 M
b0 @
b0 E
b0 J
b0 N
b0 ]
b1000 [
b1000 c
b1000 g
b1000 '"
b0 S
b0 _
b0 $"
b0 T
b0 !"
b0 ""
b1 !
b1 &
b1 ,
b1 2
b1 Q
b1 ~
b1 &"
b1100011 C
b1100011 K
b0 A
b0 G
b101 z
b100 {
b1000 |
b11000 X
b11000 m
b11000 o
b10000101000010001100011 )
b10000101000010001100011 /
b10000101000010001100011 0
b10000101000010001100011 O
b10000101000010001100011 a
b101 .
b11100 Y
b11100 h
b11100 k
b11000 W
b11000 e
b11000 j
b11000 w
b10100 (
b10100 8
b10100 Z
b10100 f
b10100 i
b10100 q
1$
#125000
0$
