ex2/top.v
/*
 * Based on D. M. Harris and S. L. Harris, "Digital Design and Computer Architecture"
 */
`timescale 1ns / 1ps
 // rename for your .dat-file
`define DATFILE "memfile.dat"

module dmem(
    input  clk, we,
    input  [31:0] a, wd,
    output [31:0] rd);

   reg [31:0] RAM[63:0];
   assign rd = RAM[a[31:2]];
	
   always @ (posedge clk)
     if (we)
       RAM[a[31:2]] <= wd;

   initial
     begin
	$readmemh (`DATFILE, RAM);
     end

endmodule

module imem (
    input  [5:0]  a,
    output [31:0] rd);
				
   reg [31:0]  RAM[63:0];
	
   initial
     begin
	$readmemh (`DATFILE, RAM);
     end
		
   assign rd = RAM[a];
endmodule

module top(
    input clk,
    input reset,
    output [31:0] writedata,
    output [31:0] dataaddr,
    output memwrite
    );

   wire [31:0] pc, instr, readdata;
   // instantiate a processor and memories
   riscv riscv (clk, reset, pc, instr, memwrite, dataaddr, writedata, readdata);
   imem imem (pc[7:2], instr);
   dmem dmem (clk, memwrite, dataaddr, writedata, readdata);
	
endmodule

ex3/alu.v
/*
 * From D. M. Harris and S. L. Harris, "Digital Design and Computer Architecture"
 */
`timescale 1ns / 1ps
module alu(
    input [31:0] srca,
    input [31:0] srcb,
    input [3:0] alucontrol,
    output reg [31:0] aluout,
    output reg btaken
    );

   always @ (*)
     begin
      case (alucontrol)
         4'b0000: aluout <= srca + srcb;
         4'b1000: aluout <= srca - srcb;
         4'b0010: aluout <= $signed(srca) < $signed(srcb);
         4'b0100: aluout <= srca ^ srcb;
         4'b0110: aluout <= srca | srcb;
         4'b0111: aluout <= srca & srcb;
      endcase
      case (alucontrol) // for conditonal branch
         4'b0000: btaken <= (srca == srcb) ? 1 : 0;                   // BEQ
         4'b0001: btaken <= (srca != srcb) ? 1 : 0;                   // BNE
         4'b0100: btaken <= ($signed(srca) < $signed(srcb)) ? 1 : 0;  // BLT
         4'b0101: btaken <= ($signed(srca) >= $signed(srcb)) ? 1 : 0; // BGE
         4'b0110: btaken <= (srca < srcb) ? 1 : 0;                    // BLTU
         4'b0111: btaken <= (srca >= srcb) ? 1 : 0;                   // BGEU
         default: btaken <= 0;
        endcase
     end
	
endmodule

module alutest;

   reg [31:0] opa, opb;
   reg [3:0]  aluc;
   wire [31:0] res;
   wire        btaken;
   
   alu alu1(opa, opb, aluc, res, btaken);

   initial begin
      $dumpfile("alutest.vcd");
      $dumpvars(0, alutest);
      aluc = 0; #1
      opa = 3; opb = 1;   #1
      aluc = 0; opa = 4; opb = -2; #1

      aluc = 8; #1
      opa = 3; opb = 1;   #1
      aluc = 8; opa = 4; opb = -2; #1
      aluc = 7; #1
      aluc = 6; #1
      aluc = 2; #1
      opa = 3; opb = 3; #1
      opa = 1; opb = 3; #1
      opa = -1; opb = 3; #1
      opa = -1; opb = -2; #1
      opa = -3; opb = -2; #1
      $finish;
   end
   

endmodule // alutest

ex3/datapath.v
/*
 * Based on D. M. Harris and S. L. Harris, "Digital Design and Computer Architecture"
 */
`timescale 1ns / 1ps
module adder(
    input  [31:0] a, b,
    output [31:0] y);

   assign y = a + b;
endmodule

module immext (
    input  i_op,
    input  s_op,
    input  b_op,
    input  u_op,
    input  j_op,
    input [31:0] instr,
    output reg [31:0] y);

   wire [4:0] immtype;

   assign immtype = { i_op, s_op, b_op, u_op, j_op };
   
   always @ (*)
     case (immtype)
       5'b10000: y <= { {20{instr[31]}}, instr[31:20] };
       5'b01000: y <= { {20{instr[31]}}, instr[31:25], instr[11:7] };
       5'b00100: y <= { {19{instr[31]}}, instr[31], instr[7], instr[30:25], instr[11:8], 1'b0 };
       5'b00010: y <= { instr[31:12], 12'b0 };
       5'b00001: y <= { {11{instr[31]}}, instr[31], instr[19:12], instr[20], instr[30:21], 1'b0 };
       default: y <= 'hx;
     endcase // case (immtpe)
   
endmodule

module flopr # (parameter WIDTH = 8)
   (input	clk, reset,
    input	[WIDTH-1:0] d,
    output reg [WIDTH-1:0]  q);
					
   always @ (posedge clk, posedge reset)
     if (reset) q <= 0;
     else	q <= d;
endmodule

module mux2 # (parameter WIDTH = 8)
   (input  [WIDTH-1:0] d0, d1,
    input  s,
    output [WIDTH-1:0] y);
				
   assign y = s ? d1 : d0;
endmodule

module regfile(
    input clk,
    input we3,
    input [4:0] ra1,
    input [4:0] ra2,
    input [4:0] wa3,
    input [31:0] wd3,
    output [31:0] rd1,
    output [31:0] rd2
    );

   reg [31:0] 	  rf[31:0];
	
   // 3-port register file
   always @ (posedge clk)
     if (we3) rf[wa3] <= wd3;
		
   assign rd1 = (ra1 != 0) ? rf[ra1] : 0;
   assign rd2 = (ra2 != 0) ? rf[ra2] : 0;
endmodule

module datapath(
    input  clk,
    input  reset,
    input  memtoreg,
    input  pcsrc,
    input  alusrc,
    input  regwrite,
    input  i_op,
    input  s_op,
    input  b_op,
    input  u_op,
    input  j_op,
    input  [3:0] alucontrol,
    output btaken,
    output [31:0] pc,
    input  [31:0] instr,
    output [31:0] aluout,
    output [31:0] writedata,
    input  [31:0] readdata
    );

   wire [31:0] 	 pcnext, pcplus4, pcbranch;
   wire [31:0] 	 immextv;
   wire [31:0] 	 rsrca, srca, srcb;
   wire [31:0] 	 result0, result;
	
   // exploit immediate
   immext	ie(i_op, s_op, b_op, u_op, j_op, instr, immextv);

   // for next PC
   flopr #(32)	pcreg(clk, reset, pcnext, pc);
   adder	pcadd1 (pc, 32'b100, pcplus4);
   adder	pcadd2(pc, immextv, pcbranch);
   mux2 #(32)   pcmux(pcplus4, pcbranch, (pcsrc|j_op), pcnext);
							
   // reg-file logic
   regfile	rf(clk, regwrite, instr[19:15], instr[24:20], instr[11:7],
		   result, rsrca, writedata);
   mux2 #(32)	resmux1(aluout, readdata, memtoreg, result0);
   mux2 #(32)	resmux2(result0, pcplus4, j_op, result);
	
   // ALU logic
   mux2 #(32) srcamux(rsrca, 32'h0, u_op, srca);
   mux2 #(32) srcbmux(writedata, immextv, alusrc, srcb);
   alu alu(srca, srcb, alucontrol, aluout, btaken);
endmodule

module testdp;
   reg clk;
   reg reset;
   reg memtoreg, pcsrc, alusrc, regwrite;
   reg i_op, s_op, b_op, u_op, j_op;
   reg [3:0] alucontrol;
   reg [31:0] instr;
   reg [31:0] readdata;
   wire btaken;
   wire [31:0] pc;
   wire [31:0] aluout;
   wire [31:0] writedata;

   datapath dp(clk, reset, memtoreg, pcsrc, alusrc, regwrite,
	       i_op, s_op, b_op, u_op, j_op, alucontrol, btaken, pc,
	       instr, aluout, writedata, readdata);

   initial begin
      $dumpfile("testdp.vcd");
      $dumpvars(0, testdp);
      clk = 1; reset = 1; memtoreg = 0; pcsrc = 0; alusrc = 0; regwrite = 1;
      instr = 32'hdeadbeaf;
      i_op = 0; s_op = 0; b_op = 0; u_op = 0; j_op = 0;
      alucontrol = 0;
      readdata = 0; #1
      reset = 0; clk = 0; #1
      clk = 1; #1
      clk = 0; #1
      clk = 1; i_op = 1; #1
      clk = 0; #1
      clk = 1; i_op = 0; s_op = 1; #1
      clk = 0; #1
      clk = 1; s_op = 0; b_op = 1; #1
      clk = 0; #1
      clk = 1; b_op = 0; u_op = 1; #1
      clk = 0; #1
      clk = 1; u_op = 0; j_op = 1; #1
      clk = 0; #1
      clk = 1; instr = 32'h5eadbeaf; j_op = 0; i_op = 1; #1
      clk = 0; #1
      clk = 1; i_op = 0; s_op = 1; #1
      clk = 0; #1
      clk = 1; s_op = 0; b_op = 1; #1
      clk = 0; #1
      clk = 1; b_op = 0; u_op = 1; #1
      clk = 0; #1
      clk = 1; u_op = 0; j_op = 1; #1
      clk = 0; #1
      clk = 1; readdata = 32'hf; memtoreg = 1; regwrite = 1; j_op = 0; i_op = 1; instr = 32'hde108080; #1
      clk = 0; #1
      clk = 1; #1
      clk = 0; #1
      clk = 1; regwrite = 0; alusrc = 0; #1
      clk = 0; #1
      clk = 1; alusrc = 1; #1
      clk = 0; #1
      clk = 1; pcsrc = 1; #1
      clk = 0; #1
      clk = 1; #1
      clk = 0; #1
      $finish;
   end
endmodule // testdp

ex3/controller.v
/*
 * Based on D. M. Harris and S. L. Harris, "Digital Design and Computer Architecture"
 */
`timescale 1ns / 1ps
module maindec(
    input [6:0] op,
    output memtoreg,
    output memwrite,
    output alusrc,
    output regwrite,
    output r_op,
    output i_op,
    output s_op,
    output b_op,
    output u_op,
    output j_op,

    output [2:0] aluop
    );

   reg [12:0] 	 controls;
	
   assign { regwrite, alusrc, memwrite, memtoreg,
            r_op, i_op, s_op, b_op, u_op, j_op, aluop } = controls;
				
   always @ (*)
     case (op)
       7'b0110011: controls <= 13'b1000100000100; //Rtype
       7'b0010011: controls <= 13'b1100010000101; //Itype
       7'b1100011: controls <= 13'b0000000100110; //Btype
       7'b0000011: controls <= 13'b1101010000111; //LW
       7'b0100011: controls <= 13'b0110001000111; //SW
       7'b0110111: controls <= 13'b1100000010011; //LUI
       7'b1101111: controls <= 13'b1000000001000; //JAL
       default:    controls <= 13'bxxxxxxxxxxxxx; //???
     endcase

endmodule

module aludec(
    input [2:0]      funct3,
    input [6:0]      funct7,
    input            r_op,
    input [2:0]      aluop,
    output reg [3:0] alucontrol
    );

   wire exf7;
   assign exf7 = (r_op & ((funct7 == 7'b0100000 ) ? 1'b1 : ((funct7 == 7'b0000000 ) ? 1'b0 : 1'bx)));
   
   always @ (*)
     case (aluop)
       3'b000: alucontrol <= 4'b0000; // addition
       3'b011: alucontrol <= 4'b0110; // or
       3'b100: alucontrol <= {exf7, funct3}; // R-type
       3'b101: alucontrol <= {1'b0, funct3}; // I-type
       3'b110: alucontrol <= {1'b0, funct3}; // B-type
       3'b111: case (funct3) // L-type or S-type
                 3'b010: alucontrol <= 4'b0000; // LW or SW
                 default: alucontrol <= 4'bxxxx;
               endcase
      default: alucontrol <= 4'bxxxx; //???
     endcase
endmodule

module controller(
    input [6:0] op,
    input [2:0] funct3,
    input [6:0] funct7,
    input btaken,
    output memtoreg,
    output memwrite,
    output pcsrc,
    output alusrc,
    output regwrite,
    output r_op,
    output i_op,
    output s_op,
    output b_op,
    output u_op,
    output j_op,
    output [3:0] alucontrol
    );

   wire [2:0] 	 aluop;
	
   maindec md (op, memtoreg, memwrite, alusrc, regwrite,
               r_op, i_op, s_op, b_op, u_op, j_op, aluop);
   aludec ad (funct3, funct7, r_op, aluop, alucontrol);
	
   assign pcsrc = b_op & btaken;
endmodule

module testcont;
   reg [6:0] op;
   reg [2:0] funct3;
   reg [6:0] funct7;
   reg 	     btaken;
   wire      memtoreg, memwrite, pcsrc, alusrc, regwrite;
   wire      r_op, i_op, s_op, b_op, u_op, j_op;
   wire [3:0] alucontrol;

   controller ctl(op, funct3, funct7, btaken, memtoreg, memwrite, pcsrc,
		  alusrc, regwrite, r_op, i_op, s_op, b_op, u_op, j_op,
                  alucontrol);

   initial begin
      $dumpfile("testcont.vcd");
      $dumpvars(0, testcont);
      btaken = 0; op = 'h33; funct3 = 'h0; funct7 = 'h0; #1
      funct3 = 'h0; funct7 = 'h20; #1
      funct3 = 'h7; funct7 = 'h0; #1
      funct3 = 'h6; funct7 = 'h0; #1
      funct3 = 'h2; funct7 = 'h0; #1
      op = 'h3; funct3 = 2; #1
      op = 'h23; funct3 = 2; #1
      op = 'h13; funct3 = 0; #1
      op = 'h13; funct3 = 6; #1
      op = 'h37; #1
      op = 'h6f; #1
      $finish;
   end
endmodule // testcont

ex2/riscv.v
/*
 * Based on D. M. Harris and S. L. Harris, "Digital Design and Computer Architecture"
 */
`timescale 1ns / 1ps
module riscv(
    input  clk,
    input  reset,
    output [31:0] pc,
    input  [31:0] instr,
    output memwrite,
    output [31:0] aluout,
    output [31:0] writedata,
    input  [31:0] readdata
    );

   wire 	  memtoreg, branch, alusrc, regdst, regwrite, jump, btaken;
   wire [1:0] 	  immtype;
 	  
   wire [3:0] 	  alucontrol;
	
   controller ctl(instr[6:0], instr[14:12], instr[31:25], btaken,
                  memtoreg, memwrite, pcsrc, alusrc, regwrite,
                  r_op, i_op, s_op, b_op, u_op, j_op, alucontrol);
   datapath dp(clk, reset, memtoreg, pcsrc, alusrc, regwrite,
               i_op, s_op, b_op, u_op, j_op, alucontrol,
               btaken, pc, instr, aluout, writedata, readdata);
					
endmodule

ex3/testbench.v
/*
 * From D. M. Harris and S. L. Harris, "Digital Design and Computer Architecture"
 */
`timescale 1ns / 1ps
module testbench();

   reg	clk;
   reg	reset;
	
   wire [31:0] writedata, dataaddr;
   wire        memwrite;
	
   // instantiate device to be tested
   top dut (clk, reset, writedata, dataaddr, memwrite);
	
   // initialize test
   initial begin
      $dumpfile("testb.vcd");
      $dumpvars(0, testbench);
      reset <= 1; # 22; reset <= 0;
   end
		
   // generate clock to sequence tests
   always
     begin
	clk <= 1; #5; clk <= 0; #5;
     end
		
   // check results
   always @ (negedge clk)
     begin
	if (memwrite & dataaddr === 84) begin
           if (writedata === 7) begin
	      $display ("Simulation succeeded");
	      $finish;
           end else begin
	      $display ("Simulation partially succeeded");
	      $finish;
           end
	end
     end

endmodule

ex3/testb.vcd
$date
	Tue Dec  9 13:28:10 2025
$end
$version
	Icarus Verilog
$end
$timescale
	1ps
$end
$scope module testbench $end
$var wire 32 ! writedata [31:0] $end
$var wire 1 " memwrite $end
$var wire 32 # dataaddr [31:0] $end
$var reg 1 $ clk $end
$var reg 1 % reset $end
$scope module dut $end
$var wire 1 $ clk $end
$var wire 1 % reset $end
$var wire 32 & writedata [31:0] $end
$var wire 32 ' readdata [31:0] $end
$var wire 32 ( pc [31:0] $end
$var wire 1 " memwrite $end
$var wire 32 ) instr [31:0] $end
$var wire 32 * dataaddr [31:0] $end
$scope module dmem $end
$var wire 1 $ clk $end
$var wire 32 + rd [31:0] $end
$var wire 1 " we $end
$var wire 32 , wd [31:0] $end
$var wire 32 - a [31:0] $end
$upscope $end
$scope module imem $end
$var wire 6 . a [5:0] $end
$var wire 32 / rd [31:0] $end
$upscope $end
$scope module riscv $end
$var wire 1 $ clk $end
$var wire 32 0 instr [31:0] $end
$var wire 32 1 readdata [31:0] $end
$var wire 1 % reset $end
$var wire 32 2 writedata [31:0] $end
$var wire 1 3 u_op $end
$var wire 1 4 s_op $end
$var wire 1 5 regwrite $end
$var wire 1 6 r_op $end
$var wire 1 7 pcsrc $end
$var wire 32 8 pc [31:0] $end
$var wire 1 " memwrite $end
$var wire 1 9 memtoreg $end
$var wire 1 : j_op $end
$var wire 1 ; i_op $end
$var wire 1 < btaken $end
$var wire 1 = b_op $end
$var wire 1 > alusrc $end
$var wire 32 ? aluout [31:0] $end
$var wire 4 @ alucontrol [3:0] $end
$scope module ctl $end
$var wire 3 A funct3 [2:0] $end
$var wire 7 B funct7 [6:0] $end
$var wire 7 C op [6:0] $end
$var wire 1 7 pcsrc $end
$var wire 1 3 u_op $end
$var wire 1 4 s_op $end
$var wire 1 5 regwrite $end
$var wire 1 6 r_op $end
$var wire 1 " memwrite $end
$var wire 1 9 memtoreg $end
$var wire 1 : j_op $end
$var wire 1 ; i_op $end
$var wire 1 < btaken $end
$var wire 1 = b_op $end
$var wire 1 > alusrc $end
$var wire 3 D aluop [2:0] $end
$var wire 4 E alucontrol [3:0] $end
$scope module ad $end
$var wire 1 F exf7 $end
$var wire 3 G funct3 [2:0] $end
$var wire 7 H funct7 [6:0] $end
$var wire 1 6 r_op $end
$var wire 3 I aluop [2:0] $end
$var reg 4 J alucontrol [3:0] $end
$upscope $end
$scope module md $end
$var wire 7 K op [6:0] $end
$var wire 1 3 u_op $end
$var wire 1 4 s_op $end
$var wire 1 5 regwrite $end
$var wire 1 6 r_op $end
$var wire 1 " memwrite $end
$var wire 1 9 memtoreg $end
$var wire 1 : j_op $end
$var wire 1 ; i_op $end
$var wire 1 = b_op $end
$var wire 1 > alusrc $end
$var wire 3 L aluop [2:0] $end
$var reg 13 M controls [12:0] $end
$upscope $end
$upscope $end
$scope module dp $end
$var wire 4 N alucontrol [3:0] $end
$var wire 1 > alusrc $end
$var wire 1 = b_op $end
$var wire 1 $ clk $end
$var wire 1 ; i_op $end
$var wire 32 O instr [31:0] $end
$var wire 1 : j_op $end
$var wire 1 9 memtoreg $end
$var wire 1 7 pcsrc $end
$var wire 32 P readdata [31:0] $end
$var wire 1 5 regwrite $end
$var wire 1 % reset $end
$var wire 1 4 s_op $end
$var wire 1 3 u_op $end
$var wire 32 Q writedata [31:0] $end
$var wire 32 R srcb [31:0] $end
$var wire 32 S srca [31:0] $end
$var wire 32 T rsrca [31:0] $end
$var wire 32 U result0 [31:0] $end
$var wire 32 V result [31:0] $end
$var wire 32 W pcplus4 [31:0] $end
$var wire 32 X pcnext [31:0] $end
$var wire 32 Y pcbranch [31:0] $end
$var wire 32 Z pc [31:0] $end
$var wire 32 [ immextv [31:0] $end
$var wire 1 < btaken $end
$var wire 32 \ aluout [31:0] $end
$scope module alu $end
$var wire 4 ] alucontrol [3:0] $end
$var wire 32 ^ srcb [31:0] $end
$var wire 32 _ srca [31:0] $end
$var reg 32 ` aluout [31:0] $end
$var reg 1 < btaken $end
$upscope $end
$scope module ie $end
$var wire 1 = b_op $end
$var wire 1 ; i_op $end
$var wire 32 a instr [31:0] $end
$var wire 1 : j_op $end
$var wire 1 4 s_op $end
$var wire 1 3 u_op $end
$var wire 5 b immtype [4:0] $end
$var reg 32 c y [31:0] $end
$upscope $end
$scope module pcadd1 $end
$var wire 32 d b [31:0] $end
$var wire 32 e y [31:0] $end
$var wire 32 f a [31:0] $end
$upscope $end
$scope module pcadd2 $end
$var wire 32 g b [31:0] $end
$var wire 32 h y [31:0] $end
$var wire 32 i a [31:0] $end
$upscope $end
$scope module pcmux $end
$var wire 32 j d0 [31:0] $end
$var wire 32 k d1 [31:0] $end
$var wire 1 l s $end
$var wire 32 m y [31:0] $end
$var parameter 32 n WIDTH $end
$upscope $end
$scope module pcreg $end
$var wire 1 $ clk $end
$var wire 32 o d [31:0] $end
$var wire 1 % reset $end
$var parameter 32 p WIDTH $end
$var reg 32 q q [31:0] $end
$upscope $end
$scope module resmux1 $end
$var wire 32 r d0 [31:0] $end
$var wire 32 s d1 [31:0] $end
$var wire 1 9 s $end
$var wire 32 t y [31:0] $end
$var parameter 32 u WIDTH $end
$upscope $end
$scope module resmux2 $end
$var wire 32 v d0 [31:0] $end
$var wire 32 w d1 [31:0] $end
$var wire 1 : s $end
$var wire 32 x y [31:0] $end
$var parameter 32 y WIDTH $end
$upscope $end
$scope module rf $end
$var wire 1 $ clk $end
$var wire 5 z ra1 [4:0] $end
$var wire 5 { ra2 [4:0] $end
$var wire 5 | wa3 [4:0] $end
$var wire 32 } wd3 [31:0] $end
$var wire 1 5 we3 $end
$var wire 32 ~ rd2 [31:0] $end
$var wire 32 !" rd1 [31:0] $end
$upscope $end
$scope module srcamux $end
$var wire 32 "" d0 [31:0] $end
$var wire 32 #" d1 [31:0] $end
$var wire 1 3 s $end
$var wire 32 $" y [31:0] $end
$var parameter 32 %" WIDTH $end
$upscope $end
$scope module srcbmux $end
$var wire 32 &" d0 [31:0] $end
$var wire 32 '" d1 [31:0] $end
$var wire 1 > s $end
$var wire 32 (" y [31:0] $end
$var parameter 32 )" WIDTH $end
$upscope $end
$upscope $end
$upscope $end
$upscope $end
$upscope $end
$enddefinitions $end
$comment Show the parameter values. $end
$dumpall
b100000 )"
b100000 %"
b100000 y
b100000 u
b100000 p
b100000 n
$end
#0
$dumpvars
b1010 ("
b1010 '"
bx &"
b0 $"
b0 #"
b0 ""
b0 !"
bx ~
b1010 }
b1 |
b1010 {
b0 z
b1010 x
b100 w
b1010 v
b1010 t
b11111111101100000000000110010011 s
b1010 r
b0 q
b100 o
b100 m
0l
b1010 k
b100 j
b0 i
b1010 h
b1010 g
b0 f
b100 e
b100 d
b1010 c
b10000 b
b101000000000000010010011 a
b1010 `
b0 _
b1010 ^
b0 ]
b1010 \
b1010 [
b0 Z
b1010 Y
b100 X
b100 W
b1010 V
b1010 U
b0 T
b0 S
b1010 R
bx Q
b11111111101100000000000110010011 P
b101000000000000010010011 O
b0 N
b1100010000101 M
b101 L
b10011 K
b0 J
b101 I
b0 H
b0 G
0F
b0 E
b101 D
b10011 C
b0 B
b0 A
b0 @
b1010 ?
1>
0=
0<
1;
0:
09
b0 8
07
06
15
04
03
bx 2
b11111111101100000000000110010011 1
b101000000000000010010011 0
b101000000000000010010011 /
b0 .
b1010 -
bx ,
b11111111101100000000000110010011 +
b1010 *
b101000000000000010010011 )
b0 (
b11111111101100000000000110010011 '
bx &
1%
1$
b1010 #
0"
bx !
$end
#5000
0$
#10000
1$
#15000
0$
#20000
1$
#22000
0%
#25000
0$
#30000
b10100 V
b10100 x
b10100 }
b10100 U
b10100 t
b10100 v
b10000100001001110001100011 '
b10000100001001110001100011 +
b10000100001001110001100011 1
b10000100001001110001100011 P
b10000100001001110001100011 s
b10100 #
b10100 *
b10100 -
b10100 ?
b10100 \
b10100 `
b10100 r
b10100 R
b10100 ^
b10100 ("
b10100 [
b10100 c
b10100 g
b10100 '"
b10100 {
b10 |
b1000 X
b1000 m
b1000 o
b1010000000000000100010011 )
b1010000000000000100010011 /
b1010000000000000100010011 0
b1010000000000000100010011 O
b1010000000000000100010011 a
b1 .
b11000 Y
b11000 h
b11000 k
b1000 W
b1000 e
b1000 j
b1000 w
b100 (
b100 8
b100 Z
b100 f
b100 i
b100 q
1$
#35000
0$
#40000
b11111111111111111111111111111011 V
b11111111111111111111111111111011 x
b11111111111111111111111111111011 }
b11111111111111111111111111111011 U
b11111111111111111111111111111011 t
b11111111111111111111111111111011 v
bx '
bx +
bx 1
bx P
bx s
b11111111111111111111111111111011 #
b11111111111111111111111111111011 *
b11111111111111111111111111111011 -
b11111111111111111111111111111011 ?
b11111111111111111111111111111011 \
b11111111111111111111111111111011 `
b11111111111111111111111111111011 r
b11111111111111111111111111111011 R
b11111111111111111111111111111011 ^
b11111111111111111111111111111011 ("
b11111111111111111111111111111011 [
b11111111111111111111111111111011 c
b11111111111111111111111111111011 g
b11111111111111111111111111111011 '"
b1111111 B
b1111111 H
b11011 {
b11 |
b1100 X
b1100 m
b1100 o
b11111111101100000000000110010011 )
b11111111101100000000000110010011 /
b11111111101100000000000110010011 0
b11111111101100000000000110010011 O
b11111111101100000000000110010011 a
b10 .
b11 Y
b11 h
b11 k
b1100 W
b1100 e
b1100 j
b1100 w
b1000 (
b1000 8
b1000 Z
b1000 f
b1000 i
b1000 q
1$
#45000
0$
#50000
1l
17
1<
b101 V
b101 x
b101 }
b101 U
b101 t
b101 v
b1010000000000000100010011 '
b1010000000000000100010011 +
b1010000000000000100010011 1
b1010000000000000100010011 P
b1010000000000000100010011 s
05
0>
0;
b100 b
1=
b110 D
b110 I
b110 L
b10100 R
b10100 ^
b10100 ("
b101 #
b101 *
b101 -
b101 ?
b101 \
b101 `
b101 r
b100110 M
b1 @
b1 E
b1 J
b1 N
b1 ]
b1000 [
b1000 c
b1000 g
b1000 '"
b1010 S
b1010 _
b1010 $"
b1010 T
b1010 !"
b1010 ""
b10100 !
b10100 &
b10100 ,
b10100 2
b10100 Q
b10100 ~
b10100 &"
b1100011 C
b1100011 K
b1 A
b1 G
b0 B
b0 H
b1 z
b10 {
b1000 |
b10100 X
b10100 m
b10100 o
b1000001001010001100011 )
b1000001001010001100011 /
b1000001001010001100011 0
b1000001001010001100011 O
b1000001001010001100011 a
b11 .
b10100 Y
b10100 h
b10100 k
b10000 W
b10000 e
b10000 j
b10000 w
b1100 (
b1100 8
b1100 Z
b1100 f
b1100 i
b1100 q
1$
#55000
0$
#60000
0l
07
0<
b111000 [
b111000 c
b111000 g
b111000 '"
b1010 R
b1010 ^
b1010 ("
b1010 !
b1010 &
b1010 ,
b1010 2
b1010 Q
b1010 ~
b1010 &"
b1 B
b1 H
b1 {
b11000 |
b11000 X
b11000 m
b11000 o
b10000100001001110001100011 )
b10000100001001110001100011 /
b10000100001001110001100011 0
b10000100001001110001100011 O
b10000100001001110001100011 a
b101 .
b1001100 Y
b1001100 h
b1001100 k
b11000 W
b11000 e
b11000 j
b11000 w
b10100 (
b10100 8
b10100 Z
b10100 f
b10100 i
b10100 q
1$
#65000
0$
#70000
b11110 V
b11110 x
b11110 }
b11110 U
b11110 t
b11110 v
b11000000000000000001101111 '
b11000000000000000001101111 +
b11000000000000000001101111 1
b11000000000000000001101111 P
b11000000000000000001101111 s
b11110 #
b11110 *
b11110 -
b11110 ?
b11110 \
b11110 `
b11110 r
1l
17
1<
b100 @
b100 E
b100 J
b100 N
b100 ]
b1000 [
b1000 c
b1000 g
b1000 '"
b10100 R
b10100 ^
b10100 ("
b10100 !
b10100 &
b10100 ,
b10100 2
b10100 Q
b10100 ~
b10100 &"
b100 A
b100 G
b0 B
b0 H
b10 {
b1000 |
b100000 X
b100000 m
b100000 o
b1000001100010001100011 )
b1000001100010001100011 /
b1000001100010001100011 0
b1000001100010001100011 O
b1000001100010001100011 a
b110 .
b100000 Y
b100000 h
b100000 k
b11100 W
b11100 e
b11100 j
b11100 w
b11000 (
b11000 8
b11000 Z
b11000 f
b11000 i
b11000 q
1$
#75000
0$
#80000
0l
07
0<
b101100 [
b101100 c
b101100 g
b101100 '"
b10100 S
b10100 _
b10100 $"
b1010 R
b1010 ^
b1010 ("
b10100 T
b10100 !"
b10100 ""
b1010 !
b1010 &
b1010 ,
b1010 2
b1010 Q
b1010 ~
b1010 &"
b1 B
b1 H
b10 z
b1 {
b1100 |
b100100 X
b100100 m
b100100 o
b10000100010100011001100011 )
b10000100010100011001100011 /
b10000100010100011001100011 0
b10000100010100011001100011 O
b10000100010100011001100011 a
b1000 .
b1001100 Y
b1001100 h
b1001100 k
b100100 W
b100100 e
b100100 j
b100100 w
b100000 (
b100000 8
b100000 Z
b100000 f
b100000 i
b100000 q
1$
#85000
0$
#90000
1l
17
1<
b101 @
b101 E
b101 J
b101 N
b101 ]
b1000 [
b1000 c
b1000 g
b1000 '"
b101 A
b101 G
b0 B
b0 H
b1000 |
b101100 X
b101100 m
b101100 o
b100010101010001100011 )
b100010101010001100011 /
b100010101010001100011 0
b100010101010001100011 O
b100010101010001100011 a
b1001 .
b101100 Y
b101100 h
b101100 k
b101000 W
b101000 e
b101000 j
b101000 w
b100100 (
b100100 8
b100100 Z
b100100 f
b100100 i
b100100 q
1$
#95000
0$
#100000
0l
07
0<
b100000 [
b100000 c
b100000 g
b100000 '"
b1010 S
b1010 _
b1010 $"
b10100 R
b10100 ^
b10100 ("
b1010 T
b1010 !"
b1010 ""
b10100 !
b10100 &
b10100 ,
b10100 2
b10100 Q
b10100 ~
b10100 &"
b1 B
b1 H
b1 z
b10 {
b0 |
b110000 X
b110000 m
b110000 o
b10001000001101000001100011 )
b10001000001101000001100011 /
b10001000001101000001100011 0
b10001000001101000001100011 O
b10001000001101000001100011 a
b1011 .
b1001100 Y
b1001100 h
b1001100 k
b110000 W
b110000 e
b110000 j
b110000 w
b101100 (
b101100 8
b101100 Z
b101100 f
b101100 i
b101100 q
1$
#105000
0$
#110000
b11111111111111111111111111111011 V
b11111111111111111111111111111011 x
b11111111111111111111111111111011 }
b11111111111111111111111111111011 U
b11111111111111111111111111111011 t
b11111111111111111111111111111011 v
bx '
bx +
bx 1
bx P
bx s
b11111111111111111111111111111011 #
b11111111111111111111111111111011 *
b11111111111111111111111111111011 -
b11111111111111111111111111111011 ?
b11111111111111111111111111111011 \
b11111111111111111111111111111011 `
b11111111111111111111111111111011 r
1l
17
1<
b110 @
b110 E
b110 J
b110 N
b110 ]
b1000 [
b1000 c
b1000 g
b1000 '"
b11111111111111111111111111111011 R
b11111111111111111111111111111011 ^
b11111111111111111111111111111011 ("
b11111111111111111111111111111011 !
b11111111111111111111111111111011 &
b11111111111111111111111111111011 ,
b11111111111111111111111111111011 2
b11111111111111111111111111111011 Q
b11111111111111111111111111111011 ~
b11111111111111111111111111111011 &"
b110 A
b110 G
b0 B
b0 H
b11 {
b1000 |
b111000 X
b111000 m
b111000 o
b1100001110010001100011 )
b1100001110010001100011 /
b1100001110010001100011 0
b1100001110010001100011 O
b1100001110010001100011 a
b1100 .
b111000 Y
b111000 h
b111000 k
b110100 W
b110100 e
b110100 j
b110100 w
b110000 (
b110000 8
b110000 Z
b110000 f
b110000 i
b110000 q
1$
#115000
0$
#120000
b1010 V
b1010 x
b1010 }
b1010 U
b1010 t
b1010 v
b11111111101100000000000110010011 '
b11111111101100000000000110010011 +
b11111111101100000000000110010011 1
b11111111101100000000000110010011 P
b11111111101100000000000110010011 s
b1010 #
b1010 *
b1010 -
b1010 ?
b1010 \
b1010 `
b1010 r
1l
17
1<
b111 @
b111 E
b111 J
b111 N
b111 ]
b11111111111111111111111111111011 S
b11111111111111111111111111111011 _
b11111111111111111111111111111011 $"
b1010 R
b1010 ^
b1010 ("
b11111111111111111111111111111011 T
b11111111111111111111111111111011 !"
b11111111111111111111111111111011 ""
b1010 !
b1010 &
b1010 ,
b1010 2
b1010 Q
b1010 ~
b1010 &"
b111 A
b111 G
b11 z
b1 {
b1000000 X
b1000000 m
b1000000 o
b100011111010001100011 )
b100011111010001100011 /
b100011111010001100011 0
b100011111010001100011 O
b100011111010001100011 a
b1110 .
b1000000 Y
b1000000 h
b1000000 k
b111100 W
b111100 e
b111100 j
b111100 w
b111000 (
b111000 8
b111000 Z
b111000 f
b111000 i
b111000 q
1$
#125000
0$
